stereomideval/__init__.py
stereomideval/dataset.py
stereomideval/eval.py
stereomideval/exceptions.py
stereomideval/structures.py
stereo_mideval-1.0.28.dist-info/METADATA
stereo_mideval-1.0.28.dist-info/WHEEL
stereo_mideval-1.0.28.dist-info/top_level.txt
stereo_mideval-1.0.28.dist-info/RECORD
