Metadata-Version: 2.1
Name: stereo-mideval
Version: 1.0.28
Summary: Evaluation dataset and tools from Middlebury Stereo Evaulation data 2014.
Home-page: https://github.com/i3drobotics/stereomideval
Author: Ben Knight
Author-email: bknight@i3drobotics.com
License: UNKNOWN
Platform: UNKNOWN
Classifier: Programming Language :: Python :: 3
Classifier: License :: OSI Approved :: MIT License
Classifier: Operating System :: OS Independent
Requires-Python: >=3.5
Requires-Dist: opencv-python
Requires-Dist: requests
Requires-Dist: wget
Requires-Dist: beautifulsoup4
Requires-Dist: numpy ; python_version == "3.5"
Requires-Dist: numpy (==1.19.3) ; python_version > "3.5"
